kolya/DeltaBR.py
kolya/DeltaBR_HO.py
kolya/DeltaBR_NP.py
kolya/DeltaBR_SM.py
kolya/Elmoments.py
kolya/Elmoments_HO.py
kolya/Elmoments_NP.py
kolya/Elmoments_SM.py
kolya/HQEparametersRGE.py
kolya/MXmoments.py
kolya/MXmoments_HO.py
kolya/MXmoments_NP.py
kolya/MXmoments_SM.py
kolya/NLOpartonic.py
kolya/NLOpw.py
kolya/NNLOpartonic.py
kolya/Q2moments.py
kolya/Q2moments_HO.py
kolya/Q2moments_HO_RPI.py
kolya/Q2moments_NP.py
kolya/Q2moments_SM.py
kolya/TotalRate.py
kolya/TotalRate_HO.py
kolya/TotalRate_HO_RPI.py
kolya/TotalRate_NP.py
kolya/TotalRate_SM.py
kolya/__init__.py
kolya/functions.py
kolya/interface_rundec.py
kolya/parameters.py
kolya/schemechange_KINMS.py
kolya/grids/__init__.py
kolya/grids/NLOpartonic/__init__.py
kolya/grids/NLOpartonic/grid_SM_Elmoments_DerivativeEl.py
kolya/grids/NLOpartonic/grid_SM_Elmoments_Derivativer.py
kolya/grids/NLOpartonic/grid_SM_Q2moments_DerivativeQ2.py
kolya/grids/NLOpartonic/grid_SM_Q2moments_Derivativer.py
kolya/grids/NLOpartonic/grid_SM_mixmoments_DerivativeEl.py
kolya/grids/NLOpartonic/grid_SM_mixmoments_Derivativer.py
kolya/grids/NLOpartonic/grid_np_Elmoments.py
kolya/grids/NLOpartonic/grid_np_Q2moments.py
kolya/grids/NLOpartonic/grid_np_mixmoments.py
kolya/grids/NLOpw/__init__.py
kolya/grids/NLOpw/grid_NLO_MuG_Elmoments.py
kolya/grids/NLOpw/grid_NLO_MuG_Q2moments.py
kolya/grids/NLOpw/grid_NLO_MuG_mixmoments.py
kolya/grids/NLOpw/grid_NLO_MuPi_Elmoments.py
kolya/grids/NLOpw/grid_NLO_MuPi_mixmoments.py
kolya/grids/NLOpw/grid_NLO_RhoD_Q2moments.py
kolya/grids/NNLOpartonic/__init__.py
kolya/grids/NNLOpartonic/grid_BLM_Elmoments.py
kolya/grids/NNLOpartonic/grid_BLM_mixmoments.py
kolya/grids/NNLOpartonic/grid_NNLO_Q2moments.py
kolya-1.0.6.dist-info/LICENSE
kolya-1.0.6.dist-info/METADATA
kolya-1.0.6.dist-info/WHEEL
kolya-1.0.6.dist-info/top_level.txt
kolya-1.0.6.dist-info/RECORD
