Metadata-Version: 2.2
Name: kolya
Version: 1.0.6
Summary: A python library for the phenomenology of B -> X l v inclusive decays.
Home-page: https://gitlab.com/vcb-inclusive/kolya
Author: Matteo Fael, Ilija S. Milutinb, K. Keri Vos
Author-email: matteo.fael@cern.ch
License: GNU GENERAL PUBLIC LICENSE V3.0
Requires-Python: >=3.6
License-File: LICENSE
Requires-Dist: scipy
Requires-Dist: numpy
Requires-Dist: numba
Requires-Dist: rundec
Dynamic: author
Dynamic: author-email
Dynamic: description
Dynamic: description-content-type
Dynamic: home-page
Dynamic: license
Dynamic: requires-dist
Dynamic: requires-python
Dynamic: summary
